FlizanApi_Py/__init__.py
FlizanApi_Py/server.py
flizanapi_py-0.0.1.dist-info/METADATA
flizanapi_py-0.0.1.dist-info/WHEEL
flizanapi_py-0.0.1.dist-info/licenses/LICENSE.txt
flizanapi_py-0.0.1.dist-info/RECORD
